oarepo_model_builder_multilingual/__init__.py
oarepo_model_builder_multilingual/faker.py
oarepo_model_builder_multilingual/builders/__init__.py
oarepo_model_builder_multilingual/builders/mult_setup_cfg.py
oarepo_model_builder_multilingual/builtin_models/__init__.py
oarepo_model_builder_multilingual/builtin_models/i18n.json
oarepo_model_builder_multilingual/datatypes/__init__.py
oarepo_model_builder_multilingual/datatypes/multilings.py
oarepo_model_builder_multilingual/datatypes/components/__init__.py
oarepo_model_builder_multilingual/datatypes/components/facets/__init__.py
oarepo_model_builder_multilingual/datatypes/components/facets/i18n.py
oarepo_model_builder_multilingual/datatypes/components/mapping/__init__.py
oarepo_model_builder_multilingual/datatypes/components/mapping/field.py
oarepo_model_builder_multilingual/datatypes/components/mapping/multi.py
oarepo_model_builder_multilingual/datatypes/components/marshmallow/__init__.py
oarepo_model_builder_multilingual/datatypes/components/marshmallow/i18n.py
oarepo_model_builder_multilingual/datatypes/components/marshmallow/ui_i18n.py
oarepo_model_builder_multilingual/datatypes/components/model/__init__.py
oarepo_model_builder_multilingual/datatypes/components/model/multilingual_dumper.py
oarepo_model_builder_multilingual/datatypes/components/multilingual/__init__.py
oarepo_model_builder_multilingual/datatypes/components/multilingual/field.py
oarepo_model_builder_multilingual/invenio/__init__.py
oarepo_model_builder_multilingual/invenio/invenio_multilingual_poetry.py
oarepo_model_builder_multilingual/invenio/invenio_record_dumper_multilingual.py
oarepo_model_builder_multilingual/invenio/invenio_record_multilingual_facets.py
oarepo_model_builder_multilingual/invenio/templates/__init__.py
oarepo_model_builder_multilingual/invenio/templates/invenio_record_dumper_multilingual.py.jinja2
oarepo_model_builder_multilingual/utils/__init__.py
oarepo_model_builder_multilingual/utils/supported_langs.py
oarepo_model_builder_multilingual-3.0.21.dist-info/licenses/LICENSE
oarepo_model_builder_multilingual-3.0.21.dist-info/METADATA
oarepo_model_builder_multilingual-3.0.21.dist-info/WHEEL
oarepo_model_builder_multilingual-3.0.21.dist-info/entry_points.txt
oarepo_model_builder_multilingual-3.0.21.dist-info/top_level.txt
oarepo_model_builder_multilingual-3.0.21.dist-info/RECORD
