Metadata-Version: 2.4
Name: oarepo-model-builder-multilingual
Version: 3.0.21
License-File: LICENSE
Requires-Dist: oarepo-model-builder-tests>=2.0.0
Requires-Dist: langcodes>=3.3.0
Provides-Extra: tests
Requires-Dist: pytest; extra == "tests"
Dynamic: license-file
